mechanica-0.0.30.dev4.data/purelib/mechanica/__init__.py
mechanica-0.0.30.dev4.data/purelib/mechanica/_mechanica.so
mechanica-0.0.30.dev4.data/purelib/mechanica/jwidget.py
mechanica-0.0.30.dev4.data/purelib/mechanica/lattice.py
mechanica-0.0.30.dev4.data/purelib/mechanica/mechanica.py
mechanica-0.0.30.dev4.data/purelib/mechanica/examples/argon.py
mechanica-0.0.30.dev4.data/purelib/mechanica/examples/argon_tstat.py
mechanica-0.0.30.dev4.data/purelib/mechanica/examples/become_1.py
mechanica-0.0.30.dev4.data/purelib/mechanica/examples/bond_ball.py
mechanica-0.0.30.dev4.data/purelib/mechanica/examples/bonded_beads.py
mechanica-0.0.30.dev4.data/purelib/mechanica/examples/bonded_sc_lattice.py
mechanica-0.0.30.dev4.data/purelib/mechanica/examples/bonded_sphere.py
mechanica-0.0.30.dev4.data/purelib/mechanica/examples/boundary1.py
mechanica-0.0.30.dev4.data/purelib/mechanica/examples/boundary_morse.py
mechanica-0.0.30.dev4.data/purelib/mechanica/examples/boundary_uptake_secrete.py
mechanica-0.0.30.dev4.data/purelib/mechanica/examples/cell_sorting.py
mechanica-0.0.30.dev4.data/purelib/mechanica/examples/change_type.py
mechanica-0.0.30.dev4.data/purelib/mechanica/examples/clipped_argon.py
mechanica-0.0.30.dev4.data/purelib/mechanica/examples/clipped_cell_sorting.py
mechanica-0.0.30.dev4.data/purelib/mechanica/examples/colormaps.py
mechanica-0.0.30.dev4.data/purelib/mechanica/examples/coupling_force.py
mechanica-0.0.30.dev4.data/purelib/mechanica/examples/cube.py
mechanica-0.0.30.dev4.data/purelib/mechanica/examples/cube2.py
mechanica-0.0.30.dev4.data/purelib/mechanica/examples/data_output.py
mechanica-0.0.30.dev4.data/purelib/mechanica/examples/dpd1.py
mechanica-0.0.30.dev4.data/purelib/mechanica/examples/dpd2.py
mechanica-0.0.30.dev4.data/purelib/mechanica/examples/dpd2new.py
mechanica-0.0.30.dev4.data/purelib/mechanica/examples/dpdtest.py
mechanica-0.0.30.dev4.data/purelib/mechanica/examples/epiboly-asym.py
mechanica-0.0.30.dev4.dist-info/METADATA
mechanica-0.0.30.dev4.dist-info/WHEEL
mechanica-0.0.30.dev4.dist-info/top_level.txt
mechanica-0.0.30.dev4.dist-info/RECORD
