Metadata-Version: 2.1
Name: mechanica
Version: 0.0.30.dev4
Summary: Interactive physics simulation engine
Home-page: https://mechanica.readthedocs.io
Author: Andy Somogyi
Author-email: andy.somogyi@gmail.com
License: LGPL
Keywords: physics,molecular dynamics,center model,sub-cellular element
Platform: Windows
Platform: Linux
Platform: Solaris
Platform: Mac OS-X
Platform: Unix
Classifier: Development Status :: 2 - Pre-Alpha
Classifier: Topic :: Scientific/Engineering :: Chemistry
Classifier: Topic :: Scientific/Engineering :: Physics
Classifier: Intended Audience :: Science/Research
Classifier: License :: OSI Approved :: GNU Lesser General Public License v2 (LGPLv2)
Classifier: Programming Language :: Python :: 3.6
Requires-Python: >=3.7.3
Requires-Dist: numpy (>=1.19.1)
